LICENSE
asynchron/__init__.py
asynchron/amqp/__init__.py
asynchron/amqp/connector.py
asynchron/amqp/consumer/__init__.py
asynchron/amqp/consumer/context.py
asynchron/amqp/consumer/factory.py
asynchron/amqp/consumer/processing.py
asynchron/amqp/controller.py
asynchron/amqp/publisher/__init__.py
asynchron/amqp/publisher/exchange.py
asynchron/amqp/publisher/factory.py
asynchron/amqp/serializer/__init__.py
asynchron/amqp/serializer/context.py
asynchron/amqp/serializer/pydantic.py
asynchron/codegen/__init__.py
asynchron/codegen/app.py
asynchron/codegen/cli/__init__.py
asynchron/codegen/cli/click_impl.py
asynchron/codegen/cli/container.py
asynchron/codegen/generator/__init__.py
asynchron/codegen/generator/container.py
asynchron/codegen/generator/jinja/__init__.py
asynchron/codegen/generator/jinja/jinja_renderer.py
asynchron/codegen/generator/jinja/python_aio_pika.py
asynchron/codegen/generator/jinja/templates/__init__.jinja2
asynchron/codegen/generator/jinja/templates/__main__.jinja2
asynchron/codegen/generator/jinja/templates/base/python_module.jinja2
asynchron/codegen/generator/jinja/templates/consumer.jinja2
asynchron/codegen/generator/jinja/templates/message.jinja2
asynchron/codegen/generator/jinja/templates/publisher.jinja2
asynchron/codegen/generator/json_schema_python_def.py
asynchron/codegen/info.py
asynchron/codegen/spec/__init__.py
asynchron/codegen/spec/asyncapi.py
asynchron/codegen/spec/document/__init__.py
asynchron/codegen/spec/document/loader.py
asynchron/codegen/spec/reader/__init__.py
asynchron/codegen/spec/reader/container.py
asynchron/codegen/spec/reader/json.py
asynchron/codegen/spec/reader/transformer.py
asynchron/codegen/spec/reader/yaml.py
asynchron/codegen/spec/transformer/__init__.py
asynchron/codegen/spec/transformer/json_reference_resolver.py
asynchron/codegen/spec/transformer/null.py
asynchron/codegen/spec/transformer/walking.py
asynchron/codegen/spec/type_definition.py
asynchron/codegen/spec/viewer/__init__.py
asynchron-0.4.0.dist-info/entry_points.txt
asynchron-0.4.0.dist-info/LICENSE
asynchron-0.4.0.dist-info/WHEEL
asynchron-0.4.0.dist-info/METADATA
asynchron-0.4.0.dist-info/RECORD
